<Properties StartupConfiguration="{15817E87-F721-4F11-8D1C-D4689A4FB1F1}|">
  <MonoDevelop.Ide.ItemProperties.Assembly-CSharp PreferredExecutionTarget="Unity.Editor" />
  <MonoDevelop.Ide.Workbench ActiveDocument="Assets/KreliUI/Scripts/UIElements/UIScreen.cs">
    <Files>
      <File FileName="Assets/ARMAth/Scripts/ModelManagers/ModelManager.cs" Line="71" Column="1" />
      <File FileName="Assets/ARMAth/Scripts/MenuManagers/RotateImage.cs" Line="1" Column="1" />
      <File FileName="Assets/ARMAth/Scripts/DataModel/Topic.cs" Line="20" Column="31" />
      <File FileName="Assets/KreliUI/Scripts/UIElements/UIButton.cs" Line="1" Column="1" />
      <File FileName="Assets/KreliUI/Scripts/Helper Class/Serializable/Actions.cs" Line="1" Column="1" />
      <File FileName="Assets/KreliUI/Scripts/UIElements/UIManager.cs" Line="82" Column="22" />
      <File FileName="Assets/KreliUI/Scripts/UIElements/UIScreen.cs" Line="61" Column="13" />
    </Files>
  </MonoDevelop.Ide.Workbench>
  <MonoDevelop.Ide.Workspace ActiveConfiguration="Debug" />
  <MonoDevelop.Ide.DebuggingService.Breakpoints>
    <BreakpointStore />
  </MonoDevelop.Ide.DebuggingService.Breakpoints>
  <MonoDevelop.Ide.DebuggingService.PinnedWatches />
  <MultiItemStartupConfigurations />
</Properties>